{
    "@odata.context": "https://94.130.48.155:50000/b1s/v2/$metadata#SAPB1.SQLQueryResult",
    "SqlText": "select [OBBQ].[OnHandQty] as [Quantity],[OBTN].[ExpDate] as [Bbd],[OBTN].[DistNumber] as [Batch],[OBIN].[AbsEntry] as [BinAbsEntry],[OBIN].[BarCode] as [BinBarCode],[OBIN].[BinCode] as [BinCode] from [OBBQ],[OBTN],[OBIN] where [OBBQ].[SnBMDAbs] = [OBTN].[AbsEntry] and [OBBQ].[BinAbs] = [OBIN].[AbsEntry] and [OBBQ].[ItemCode] = :itemCode and [OBBQ].[BinAbs] = :binAbsEntry and [OBBQ].[OnHandQty] > 0 order by [OBTN].[DistNumber]",
    "value": [
        {
            "Batch": "B1-00097",
            "Bbd": null,
            "BinAbsEntry": 10,
            "BinBarCode": null,
            "BinCode": "05-G01-R03-P01",
            "Quantity": 10.0
        },
        {
            "Batch": "B1-00098",
            "Bbd": null,
            "BinAbsEntry": 10,
            "BinBarCode": null,
            "BinCode": "05-G01-R03-P01",
            "Quantity": 20.0
        },
        {
            "Batch": "B1-00099",
            "Bbd": null,
            "BinAbsEntry": 10,
            "BinBarCode": null,
            "BinCode": "05-G01-R03-P01",
            "Quantity": 20.0
        },
        {
            "Batch": "B1-00100",
            "Bbd": null,
            "BinAbsEntry": 10,
            "BinBarCode": null,
            "BinCode": "05-G01-R03-P01",
            "Quantity": 10.0
        }
    ]
}